csv_to_xls/__init__.py
csv_to_xls/_modidx.py
csv_to_xls/core.py
csv_to_xls-0.0.4.dist-info/LICENSE
csv_to_xls-0.0.4.dist-info/METADATA
csv_to_xls-0.0.4.dist-info/WHEEL
csv_to_xls-0.0.4.dist-info/entry_points.txt
csv_to_xls-0.0.4.dist-info/top_level.txt
csv_to_xls-0.0.4.dist-info/RECORD
